chatsee/__init__.py
chatsee/tracker.py
chatsee_ai-0.2.0.dist-info/METADATA
chatsee_ai-0.2.0.dist-info/WHEEL
chatsee_ai-0.2.0.dist-info/top_level.txt
chatsee_ai-0.2.0.dist-info/RECORD
