Metadata-Version: 2.4
Name: chatsee-ai
Version: 0.2.0
Summary: A Python SDK for Chatsee AI.
Author: Chatsee Team
Author-email: kunal.golani@isynergytech.com
Classifier: Programming Language :: Python :: 3
Classifier: License :: OSI Approved :: MIT License
Classifier: Operating System :: OS Independent
Requires-Python: >=3.7
Requires-Dist: requests>=2.31.0
Dynamic: author
Dynamic: author-email
Dynamic: classifier
Dynamic: requires-dist
Dynamic: requires-python
Dynamic: summary
